LICENSE
MANIFEST.in
README.md
pyproject.toml
setup.cfg
setup.py
requirements/requirements.txt
requirements/tests.txt
requirements/typing.txt
src/flask_mixins/__init__.py
src/flask_mixins/middleware.py
src/flask_mixins/permissions.py
src/flask_mixins/views.py
src/flask_mixins.egg-info/PKG-INFO
src/flask_mixins.egg-info/SOURCES.txt
src/flask_mixins.egg-info/dependency_links.txt
src/flask_mixins.egg-info/not-zip-safe
src/flask_mixins.egg-info/requires.txt
src/flask_mixins.egg-info/top_level.txt
src/flask_mixins/view_mixins/__init__.py
src/flask_mixins/view_mixins/_utils.py
src/flask_mixins/view_mixins/misc_mixins.py
src/flask_mixins/view_mixins/permission_mixin.py
src/flask_mixins/view_mixins/schema_mixin.py
src/flask_mixins/view_mixins/service_mixin.py