Metadata-Version: 2.1
Name: flask-mixins
Version: 0.0.6
Summary: Flask and marshmallow cleaner code
Home-page: https://github.com/reritom/flask-mixins
Author: Tomas Sheers
Author-email: t.sheers@outlook.com
License: MIT
Project-URL: Issues, https://github.com/reritom/flask-mixins/issues
Keywords: flask-mixins
Platform: UNKNOWN
Classifier: Development Status :: 4 - Beta
Classifier: Environment :: Web Environment
Classifier: Intended Audience :: Developers
Classifier: License :: OSI Approved :: MIT License
Classifier: Natural Language :: English
Classifier: Programming Language :: Python :: 3
Classifier: Programming Language :: Python :: 3.8
Classifier: Topic :: Internet :: WWW/HTTP :: Dynamic Content
Requires-Python: >=3.8
